serializepy/__init__.py
serializepy/parsers.py
serializepy/utilities.py
serializepy/version.py
serializepy/visitors.py
tests/__init__.py
tests/test_deserialize_classes.py
tests/test_deserialize_general.py
tests/test_deserialize_inheritance.py
tests/test_deserialize_static.py
tests/test_serialize.py
serializepy-0.0.2.dist-info/LICENSE
serializepy-0.0.2.dist-info/METADATA
serializepy-0.0.2.dist-info/WHEEL
serializepy-0.0.2.dist-info/top_level.txt
serializepy-0.0.2.dist-info/RECORD
