Metadata-Version: 2.1
Name: serializepy
Version: 0.0.2
Summary: Serialize and deserialize using type hints
Home-page: https://github.com/jepperaskdk/serializepy
Author: Jeppe Rask
Author-email: jepperaskdk@gmail.com
License: UNKNOWN
Project-URL: Bug Tracker, https://github.com/jepperaskdk/serializepy/issues
Platform: UNKNOWN
Requires-Python: >=3.6
